vgstash_cli.py
vgstash/__init__.py
vgstash-0.3b8.dist-info/licenses/AUTHORS
vgstash-0.3b8.dist-info/licenses/LICENSE
vgstash-0.3b8.dist-info/METADATA
vgstash-0.3b8.dist-info/WHEEL
vgstash-0.3b8.dist-info/entry_points.txt
vgstash-0.3b8.dist-info/top_level.txt
vgstash-0.3b8.dist-info/RECORD
