Metadata-Version: 2.4
Name: vgstash
Version: 0.3b8
Summary: a video game collection management module, backed by SQLite
Home-page: https://git.zlg.space/vgstash
Author: zlg
Author-email: zlg+vgstash@zlg.space
License: License-Expression: AGPL-3.0-only
Project-URL: Source, https://git.zlg.space/vgstash
Classifier: Development Status :: 4 - Beta
Classifier: Operating System :: POSIX :: Linux
Classifier: Programming Language :: Python :: 3 :: Only
Classifier: Topic :: Games/Entertainment
Classifier: Topic :: Utilities
License-File: LICENSE
License-File: AUTHORS
Requires-Dist: Click>=6.0
Requires-Dist: PyYAML
Dynamic: author
Dynamic: author-email
Dynamic: classifier
Dynamic: description
Dynamic: description-content-type
Dynamic: home-page
Dynamic: license
Dynamic: license-file
Dynamic: project-url
Dynamic: requires-dist
Dynamic: summary
